detaf-0.3.1.dist-info/METADATA
detaf-0.3.1.dist-info/WHEEL
detaf-0.3.1.dist-info/entry_points.txt
detaf-0.3.1.dist-info/licenses/LICENSE
detaf/__init__.py
detaf/cloud.py
detaf/lib.py
detaf/temperature.py
detaf/wx.py
detaf-0.3.1.dist-info/RECORD
