Metadata-Version: 2.1
Name: detaf
Version: 0.3.1
Summary: Decode TAF files
Author-Email: andrewgryan <andrew.ryan@metoffice.gov.uk>
License: MIT
Requires-Python: >=3.11
Provides-Extra: test
Requires-Dist: pytest>=8.3.3; extra == "test"
Requires-Dist: hypothesis>=6.118.7; extra == "test"
Requires-Dist: pytest-watcher>=0.4.3; extra == "test"
